CHANGELOG.txt
LICENCE.txt
MANIFEST.in
README.txt
setup.py
x.py
.venv/lib/python3.12/site-packages/PROG/__init__.py
.venv/lib/python3.12/site-packages/_distutils_hack/__init__.py
.venv/lib/python3.12/site-packages/_distutils_hack/override.py
.venv/lib/python3.12/site-packages/certifi/__init__.py
.venv/lib/python3.12/site-packages/certifi/__main__.py
.venv/lib/python3.12/site-packages/certifi/core.py
.venv/lib/python3.12/site-packages/certifi-2024.7.4.dist-info/top_level.txt
.venv/lib/python3.12/site-packages/charset_normalizer/__init__.py
.venv/lib/python3.12/site-packages/charset_normalizer/__main__.py
.venv/lib/python3.12/site-packages/charset_normalizer/api.py
.venv/lib/python3.12/site-packages/charset_normalizer/cd.py
.venv/lib/python3.12/site-packages/charset_normalizer/constant.py
.venv/lib/python3.12/site-packages/charset_normalizer/legacy.py
.venv/lib/python3.12/site-packages/charset_normalizer/md.py
.venv/lib/python3.12/site-packages/charset_normalizer/models.py
.venv/lib/python3.12/site-packages/charset_normalizer/utils.py
.venv/lib/python3.12/site-packages/charset_normalizer/version.py
.venv/lib/python3.12/site-packages/charset_normalizer-3.3.2.dist-info/entry_points.txt
.venv/lib/python3.12/site-packages/charset_normalizer-3.3.2.dist-info/top_level.txt
.venv/lib/python3.12/site-packages/charset_normalizer/cli/__init__.py
.venv/lib/python3.12/site-packages/charset_normalizer/cli/__main__.py
.venv/lib/python3.12/site-packages/docutils/__init__.py
.venv/lib/python3.12/site-packages/docutils/__main__.py
.venv/lib/python3.12/site-packages/docutils/core.py
.venv/lib/python3.12/site-packages/docutils/examples.py
.venv/lib/python3.12/site-packages/docutils/frontend.py
.venv/lib/python3.12/site-packages/docutils/io.py
.venv/lib/python3.12/site-packages/docutils/nodes.py
.venv/lib/python3.12/site-packages/docutils/statemachine.py
.venv/lib/python3.12/site-packages/docutils-0.21.2.dist-info/COPYING.txt
.venv/lib/python3.12/site-packages/docutils-0.21.2.dist-info/entry_points.txt
.venv/lib/python3.12/site-packages/docutils/languages/__init__.py
.venv/lib/python3.12/site-packages/docutils/languages/af.py
.venv/lib/python3.12/site-packages/docutils/languages/ar.py
.venv/lib/python3.12/site-packages/docutils/languages/ca.py
.venv/lib/python3.12/site-packages/docutils/languages/cs.py
.venv/lib/python3.12/site-packages/docutils/languages/da.py
.venv/lib/python3.12/site-packages/importlib_metadata-8.4.0.dist-info/top_level.txt
.venv/lib/python3.12/site-packages/jaraco.classes-3.4.0.dist-info/top_level.txt
.venv/lib/python3.12/site-packages/jaraco.context-6.0.1.dist-info/top_level.txt
.venv/lib/python3.12/site-packages/jaraco.functools-4.0.2.dist-info/top_level.txt
.venv/lib/python3.12/site-packages/keyring-25.3.0.dist-info/entry_points.txt
.venv/lib/python3.12/site-packages/keyring-25.3.0.dist-info/top_level.txt
.venv/lib/python3.12/site-packages/markdown_it_py-3.0.0.dist-info/entry_points.txt
.venv/lib/python3.12/site-packages/pip-24.2.dist-info/AUTHORS.txt
.venv/lib/python3.12/site-packages/pip-24.2.dist-info/LICENSE.txt
.venv/lib/python3.12/site-packages/pip-24.2.dist-info/entry_points.txt
.venv/lib/python3.12/site-packages/pip-24.2.dist-info/top_level.txt
.venv/lib/python3.12/site-packages/pkg_resources/tests/data/my-test-package_unpacked-egg/my_test_package-1.0-py3.7.egg/EGG-INFO/SOURCES.txt
.venv/lib/python3.12/site-packages/pkg_resources/tests/data/my-test-package_unpacked-egg/my_test_package-1.0-py3.7.egg/EGG-INFO/dependency_links.txt
.venv/lib/python3.12/site-packages/pkg_resources/tests/data/my-test-package_unpacked-egg/my_test_package-1.0-py3.7.egg/EGG-INFO/top_level.txt
.venv/lib/python3.12/site-packages/pkginfo-1.10.0.dist-info/LICENSE.txt
.venv/lib/python3.12/site-packages/pkginfo-1.10.0.dist-info/entry_points.txt
.venv/lib/python3.12/site-packages/pkginfo-1.10.0.dist-info/top_level.txt
.venv/lib/python3.12/site-packages/pygments-2.18.0.dist-info/entry_points.txt
.venv/lib/python3.12/site-packages/readme_renderer-44.0.dist-info/top_level.txt
.venv/lib/python3.12/site-packages/requests-2.32.3.dist-info/top_level.txt
.venv/lib/python3.12/site-packages/requests_toolbelt-1.0.0.dist-info/top_level.txt
.venv/lib/python3.12/site-packages/rfc3986-2.0.0.dist-info/top_level.txt
.venv/lib/python3.12/site-packages/setuptools-73.0.1.dist-info/entry_points.txt
.venv/lib/python3.12/site-packages/setuptools-73.0.1.dist-info/top_level.txt
.venv/lib/python3.12/site-packages/setuptools/_vendor/autocommand-2.2.2.dist-info/top_level.txt
.venv/lib/python3.12/site-packages/setuptools/_vendor/backports.tarfile-1.2.0.dist-info/top_level.txt
.venv/lib/python3.12/site-packages/setuptools/_vendor/importlib_metadata-8.0.0.dist-info/top_level.txt
.venv/lib/python3.12/site-packages/setuptools/_vendor/importlib_resources-6.4.0.dist-info/top_level.txt
.venv/lib/python3.12/site-packages/setuptools/_vendor/inflect-7.3.1.dist-info/top_level.txt
.venv/lib/python3.12/site-packages/setuptools/_vendor/jaraco.context-5.3.0.dist-info/top_level.txt
.venv/lib/python3.12/site-packages/setuptools/_vendor/jaraco.functools-4.0.1.dist-info/top_level.txt
.venv/lib/python3.12/site-packages/setuptools/_vendor/jaraco.text-3.12.1.dist-info/top_level.txt
.venv/lib/python3.12/site-packages/setuptools/_vendor/typeguard-4.3.0.dist-info/entry_points.txt
.venv/lib/python3.12/site-packages/setuptools/_vendor/typeguard-4.3.0.dist-info/top_level.txt
.venv/lib/python3.12/site-packages/setuptools/_vendor/wheel-0.43.0.dist-info/LICENSE.txt
.venv/lib/python3.12/site-packages/setuptools/_vendor/wheel-0.43.0.dist-info/entry_points.txt
.venv/lib/python3.12/site-packages/setuptools/_vendor/zipp-3.19.2.dist-info/top_level.txt
.venv/lib/python3.12/site-packages/tellHi-0.0.3.dist-info/LICENCE.txt
.venv/lib/python3.12/site-packages/tellHi-0.0.3.dist-info/entry_points.txt
.venv/lib/python3.12/site-packages/tellHi-0.0.3.dist-info/top_level.txt
.venv/lib/python3.12/site-packages/twine-5.1.1.dist-info/entry_points.txt
