Metadata-Version: 2.1
Name: tellHi
Version: 0.0.6
Summary: A very basic hello world PROGRAMME
Home-page: 
Author: Akshat Kala
Author-email: akshatcodes706@gmail.com
License: MIT
Keywords: helloWorld
Classifier: Development Status :: 5 - Production/Stable
Classifier: Intended Audience :: Education
Classifier: Operating System :: Microsoft :: Windows :: Windows 10
Classifier: License :: OSI Approved :: MIT License
Classifier: Programming Language :: Python :: 3
License-File: LICENCE.txt
